CHANGES.txt
LICENSE.txt
MANIFEST.in
README.txt
borium.py
setup.py
python_borium.egg-info/PKG-INFO
python_borium.egg-info/SOURCES.txt
python_borium.egg-info/dependency_links.txt
python_borium.egg-info/top_level.txt