Metadata-Version: 1.0
Name: python-borium
Version: 0.1.0
Summary: Simple Get/Put API for the Borium Queue
Home-page: http://pypi.python.org/pypi/python-borium
Author: Ben Beltran
Author-email: ben@nsovocal.com
License: The MIT License (MIT)
